stlg/__init__.py
stlg/fetch_spetc_ids.py
stlg/gen_basepaths.py
stlg/gen_spetc_headers.py
stlg/spetcdb.py
stlg/testlist_gen.py
stlg/venv_setup.py
stlg_altera-0.1.2.dist-info/LICENSE
stlg_altera-0.1.2.dist-info/METADATA
stlg_altera-0.1.2.dist-info/WHEEL
stlg_altera-0.1.2.dist-info/top_level.txt
stlg_altera-0.1.2.dist-info/RECORD
