Metadata-Version: 2.1
Name: stlg-altera
Version: 0.1.2
Summary: Sample Test List Generator for SPeTCDB
Home-page: UNKNOWN
Author: Sai Kiran Gundeti
Author-email: sai.kiran.gundeti@altera.com
License: MIT
Platform: UNKNOWN
Classifier: Programming Language :: Python :: 3
Classifier: License :: OSI Approved :: MIT License
Classifier: Operating System :: OS Independent
Requires-Python: >=3.6
License-File: LICENSE
Requires-Dist: requests
Requires-Dist: pandas
